ploigos_step_runner/__init__.py
ploigos_step_runner/__main__.py
ploigos_step_runner/decryption_utils.py
ploigos_step_runner/exceptions.py
ploigos_step_runner/step_implementer.py
ploigos_step_runner/step_runner.py
ploigos_step_runner/version.py
ploigos_step_runner/config/__init__.py
ploigos_step_runner/config/config.py
ploigos_step_runner/config/config_value.py
ploigos_step_runner/config/config_value_decryptor.py
ploigos_step_runner/config/step_config.py
ploigos_step_runner/config/sub_step_config.py
ploigos_step_runner/config/decryptors/__init__.py
ploigos_step_runner/config/decryptors/sops.py
ploigos_step_runner/results/__init__.py
ploigos_step_runner/results/step_result.py
ploigos_step_runner/results/step_result_artifact.py
ploigos_step_runner/results/step_result_evidence.py
ploigos_step_runner/results/workflow_result.py
ploigos_step_runner/step_implementers/__init__.py
ploigos_step_runner/step_implementers/audit_attestation/__init__.py
ploigos_step_runner/step_implementers/audit_attestation/opa.py
ploigos_step_runner/step_implementers/container_image_static_compliance_scan/__init__.py
ploigos_step_runner/step_implementers/container_image_static_compliance_scan/openscap.py
ploigos_step_runner/step_implementers/container_image_static_vulnerability_scan/__init__.py
ploigos_step_runner/step_implementers/container_image_static_vulnerability_scan/openscap.py
ploigos_step_runner/step_implementers/create_container_image/__init__.py
ploigos_step_runner/step_implementers/create_container_image/buildah.py
ploigos_step_runner/step_implementers/create_container_image/maven_jkube_k8sbuild.py
ploigos_step_runner/step_implementers/create_container_image/source_to_image.py
ploigos_step_runner/step_implementers/deploy/__init__.py
ploigos_step_runner/step_implementers/deploy/argocd.py
ploigos_step_runner/step_implementers/deploy/argocd_deploy.py
ploigos_step_runner/step_implementers/generate_evidence/__init__.py
ploigos_step_runner-1.0.0.dist-info/COMMITMENT
ploigos_step_runner-1.0.0.dist-info/LICENSE
ploigos_step_runner-1.0.0.dist-info/METADATA
ploigos_step_runner-1.0.0.dist-info/WHEEL
ploigos_step_runner-1.0.0.dist-info/entry_points.txt
ploigos_step_runner-1.0.0.dist-info/top_level.txt
ploigos_step_runner-1.0.0.dist-info/RECORD
