Metadata-Version: 2.1
Name: ploigos-step-runner
Version: 1.0.0
Summary: Ploigos Step Runner (PSR) implemented as a Python library.
Home-page: https://github.com/ploigos/ploigos-step-runner
Author: Red Hat Services
License: UNKNOWN
Keywords: ploigos,psr,Step Runner,Trusted Software Supply Chain,Red Hat,Red Hat Services
Platform: UNKNOWN
Classifier: Programming Language :: Python :: 3.6
Classifier: Programming Language :: Python :: 3.8
Classifier: License :: OSI Approved :: GNU General Public License v3 or later (GPLv3+)
Classifier: Operating System :: OS Independent
Requires-Python: >=3.6
License-File: LICENSE
License-File: COMMITMENT
Requires-Dist: PyYAML
Requires-Dist: gitpython
Requires-Dist: sh
Requires-Dist: jinja2
Provides-Extra: tests
Requires-Dist: wheel ; extra == 'tests'
Requires-Dist: pylint ; extra == 'tests'
Requires-Dist: flake8 ; extra == 'tests'
Requires-Dist: bandit ; extra == 'tests'
Requires-Dist: pytest ; extra == 'tests'
Requires-Dist: pytest-cov ; extra == 'tests'
Requires-Dist: testfixtures ; extra == 'tests'
Requires-Dist: mock ; extra == 'tests'
Requires-Dist: codecov ; extra == 'tests'
Requires-Dist: tox ; extra == 'tests'
